[
  { "id": 1, "name": "Kabul", "country_id": 1 },
  { "id": 2, "name": "Canberra", "country_id": 2 },
  { "id": 3, "name": "Brussels", "country_id": 3 },
  { "id": 4, "name": "São Paulo", "country_id": 4 },
  { "id": 5, "name": "Toronto", "country_id": 5 },
  { "id": 6, "name": "Beijing", "country_id": 6 },
  { "id": 7, "name": "Copenhagen", "country_id": 7 },
  { "id": 8, "name": "Cairo", "country_id": 8 },
  { "id": 9, "name": "Helsinki", "country_id": 9 },
  { "id": 10, "name": "Paris", "country_id": 10 },
  { "id": 11, "name": "Berlin", "country_id": 11 },
  { "id": 12, "name": "Athens", "country_id": 12 },
  { "id": 13, "name": "Mumbai", "country_id": 13 },
  { "id": 14, "name": "Jakarta", "country_id": 14 },
  { "id": 15, "name": "Dublin", "country_id": 15 },
  { "id": 16, "name": "Tel Aviv", "country_id": 16 },
  { "id": 17, "name": "Rome", "country_id": 17 },
  { "id": 18, "name": "Tokyo", "country_id": 18 },
  { "id": 19, "name": "Nairobi", "country_id": 19 },
  { "id": 20, "name": "Kuala Lumpur", "country_id": 20 },
  { "id": 21, "name": "Mexico City", "country_id": 21 },
  { "id": 22, "name": "Amsterdam", "country_id": 22 },
  { "id": 23, "name": "Auckland", "country_id": 23 },
  { "id": 24, "name": "Oslo", "country_id": 24 },
  { "id": 25, "name": "Lahore", "country_id": 25 },
  { "id": 26, "name": "Manila", "country_id": 26 },
  { "id": 27, "name": "Warsaw", "country_id": 27 },
  { "id": 28, "name": "Lisbon", "country_id": 28 },
  { "id": 29, "name": "Moscow", "country_id": 29 },
  { "id": 30, "name": "Riyadh", "country_id": 30 },
  { "id": 31, "name": "Singapore", "country_id": 31 },
  { "id": 32, "name": "Cape Town", "country_id": 32 },
  { "id": 33, "name": "Seoul", "country_id": 33 },
  { "id": 34, "name": "Madrid", "country_id": 34 },
  { "id": 35, "name": "Stockholm", "country_id": 35 },
  { "id": 36, "name": "Zurich", "country_id": 36 },
  { "id": 37, "name": "Bangkok", "country_id": 37 },
  { "id": 38, "name": "Istanbul", "country_id": 38 },
  { "id": 39, "name": "Dubai", "country_id": 39 },
  { "id": 40, "name": "Kyiv", "country_id": 40 },
  { "id": 41, "name": "London", "country_id": 41 },
  { "id": 42, "name": "New York", "country_id": 42 },
  { "id": 43, "name": "Ho Chi Minh City", "country_id": 43 },
  { "id": 44, "name": "Buenos Aires", "country_id": 44 },
  { "id": 45, "name": "Santiago", "country_id": 45 },
  { "id": 46, "name": "Bogotá", "country_id": 46 },
  { "id": 47, "name": "Belfast", "country_id": 47 },
  { "id": 48, "name": "Prague", "country_id": 48 },
  { "id": 49, "name": "Budapest", "country_id": 49 },
  { "id": 50, "name": "Bucharest", "country_id": 50 }
]
